hatch_nuitka/__about__.py
hatch_nuitka/__init__.py
hatch_nuitka/hooks.py
hatch_nuitka/plugin.py
hatch_nuitka-0.0.4.dist-info/METADATA
hatch_nuitka-0.0.4.dist-info/WHEEL
hatch_nuitka-0.0.4.dist-info/entry_points.txt
hatch_nuitka-0.0.4.dist-info/licenses/LICENSE.txt
hatch_nuitka-0.0.4.dist-info/RECORD
