Metadata-Version: 2.1
Name: hatch-nuitka
Version: 0.0.4
Summary: hatch nuitka plugin
Project-URL: Documentation, https://github.com/HSPK/hatch-nuitka#readme
Project-URL: Issues, https://github.com/HSPK/hatch-nuitka/issues
Project-URL: Source, https://github.com/HSPK/hatch-nuitka
Author-email: HSPK <whxway@whu.edu.cn>
License-Expression: MIT
License-File: LICENSE.txt
Classifier: Development Status :: 4 - Beta
Classifier: Programming Language :: Python
Classifier: Programming Language :: Python :: 3.7
Classifier: Programming Language :: Python :: 3.8
Classifier: Programming Language :: Python :: 3.9
Classifier: Programming Language :: Python :: 3.10
Classifier: Programming Language :: Python :: 3.11
Classifier: Programming Language :: Python :: Implementation :: CPython
Classifier: Programming Language :: Python :: Implementation :: PyPy
Requires-Python: >=3.7
